word_processing
