Metadata-Version: 1.0
Name: word-processing
Version: 23.20
Summary: anayzing and preparing document for analysis
Home-page: UNKNOWN
Author: UNKNOWN
Author-email: UNKNOWN
License: UNKNOWN
Platform: UNKNOWN
